flaskbanstates/__init__.py
flask_ban_states-1.0.dist-info/METADATA
flask_ban_states-1.0.dist-info/WHEEL
flask_ban_states-1.0.dist-info/top_level.txt
flask_ban_states-1.0.dist-info/RECORD
