Metadata-Version: 2.4
Name: flask-ban-states
Version: 1.0
Summary: Библиотека для удобной блокировки людей по стране.
Author: florestdev
Author-email: florestone4185@internet.ru
Project-URL: Social Resources, https://taplink.cc/florestone4185
Project-URL: Flask, https://pypi.org/project/Flask/
Project-URL: GitHub, https://github.com/florestdev/flaskbannerstates
Requires-Python: >=3.10
Requires-Dist: flask
Requires-Dist: requests
Requires-Dist: aiohttp
Dynamic: author
Dynamic: author-email
Dynamic: description
Dynamic: project-url
Dynamic: requires-dist
Dynamic: requires-python
Dynamic: summary
